ntu_student_id/__init__.py
ntu_student_id/main.py
ntu_student_id/data/departments.json
src/__init__.py
src/main.py
src/data/departments.json
ntu_student_id-1.3.0.dist-info/METADATA
ntu_student_id-1.3.0.dist-info/WHEEL
ntu_student_id-1.3.0.dist-info/top_level.txt
ntu_student_id-1.3.0.dist-info/RECORD
