Metadata-Version: 2.1
Name: ntu-student-id
Version: 1.3.0
Summary: Get department information by NTU student ID
Home-page: https://github.com/maxchou415/ntu_student_id.py
Author: Max Yi-Hsun Chou
Author-email: Max Yi-Hsun Chou <maxchou415@gmail.com>
Project-URL: Homepage, https://github.com/maxchou415/ntu_student_id.py
Classifier: Programming Language :: Python :: 3
Classifier: Operating System :: OS Independent
Requires-Python: >=3.7
